setup.py
ann/__init__.py
ann.egg-info/PKG-INFO
ann.egg-info/SOURCES.txt
ann.egg-info/dependency_links.txt
ann.egg-info/requires.txt
ann.egg-info/top_level.txt