Metadata-Version: 1.1
Name: ann
Version: 0.1.0
Summary: Supporting package for the book 'Introduction to Artificial Neural Networks and Deep Learning: A Practical Guide with Applications in Python'
Home-page: https://github.com/rasbt/deep-learning-book
Author: Sebastian Raschka
Author-email: mail@sebastianraschka.com
License: MIT
Keywords: artificial neural networks,deep learning,machine learning,artificial intelligence,data science
Platform: UNKNOWN
Classifier: License :: OSI Approved :: MIT License
Classifier: Operating System :: Microsoft :: Windows
Classifier: Operating System :: POSIX
Classifier: Operating System :: Unix
Classifier: Operating System :: MacOS
Classifier: Programming Language :: Python :: 2.7
Classifier: Programming Language :: Python :: 3.5
Classifier: Programming Language :: Python :: 3.6
Classifier: Topic :: Scientific/Engineering
Classifier: Topic :: Scientific/Engineering :: Artificial Intelligence
Classifier: Topic :: Scientific/Engineering :: Information Analysis
Classifier: Topic :: Scientific/Engineering :: Image Recognition
